promplate_pyodide-0.0.4.dist-info/METADATA
promplate_pyodide-0.0.4.dist-info/WHEEL
promplate_pyodide-0.0.4.dist-info/entry_points.txt
promplate_pyodide/__init__.py
promplate_pyodide/utils/check.py
promplate_pyodide/utils/openai/__init__.py
promplate_pyodide/utils/openai/sync.py
promplate_pyodide/utils/proxy.py
promplate_pyodide/utils/stack_switching.py
promplate_pyodide/utils/sync.py
promplate_pyodide/utils/warn.py
promplate_pyodide-0.0.4.dist-info/RECORD
