Metadata-Version: 2.1
Name: promplate-pyodide
Version: 0.0.4
Summary: patches for promplate-core for running in pyodide runtime
Author-Email: Muspi Merol <me@promplate.dev>
License: MIT
Requires-Python: >=3.10
Requires-Dist: promplate<0.4,>=0.3.3.4
